coinbitrage/__init__.py
coinbitrage/cli.py
coinbitrage/coinbitrage.py
coinbitrage-0.1.1.dist-info/DESCRIPTION.rst
coinbitrage-0.1.1.dist-info/METADATA
coinbitrage-0.1.1.dist-info/RECORD
coinbitrage-0.1.1.dist-info/WHEEL
coinbitrage-0.1.1.dist-info/entry_points.txt
coinbitrage-0.1.1.dist-info/metadata.json
coinbitrage-0.1.1.dist-info/top_level.txt
