Metadata-Version: 2.0
Name: coinbitrage
Version: 0.1.1
Summary: Arbitrage lookup for crypto currency exchanges
Home-page: https://github.com/granitosaurus/coinbitrage
Author: Bernardas Ališauskas
Author-email: bernardas.alisauskas@protonmail.com
License: GNU General Public License v3
Keywords: coinbitrage
Platform: UNKNOWN
Classifier: Development Status :: 2 - Pre-Alpha
Classifier: Intended Audience :: Developers
Classifier: License :: OSI Approved :: GNU General Public License v3 (GPLv3)
Classifier: Natural Language :: English
Classifier: Programming Language :: Python :: 3.6
Requires-Dist: Click (>=6.0)
Requires-Dist: parsel
Requires-Dist: requests
Requires-Dist: requests
Requires-Dist: terminaltables
